orbkit/cy_overlap.cpython-37m-x86_64-linux-gnu.so
orbkit/c_non-grid-based.c
orbkit/tools.py
orbkit/options.py
orbkit/core.py
orbkit/atomic_populations.py
orbkit/analytical_integrals.py
orbkit/orbitals.py
orbkit/__init__.py
orbkit/extras.py
orbkit/units.py
orbkit/__main__.py
orbkit/cy_overlap.pyx
orbkit/c_grid-based.c
orbkit/cy_grid.cpython-37m-x86_64-linux-gnu.so
orbkit/c_support.c
orbkit/grid.py
orbkit/cy_core.cpython-37m-x86_64-linux-gnu.so
orbkit/omp_functions.py
orbkit/cy_core.pyx
orbkit/display.py
orbkit/main.py
orbkit/qcinfo.py
orbkit/cy_grid.pyx
orbkit/detci/__init__.py
orbkit/detci/cy_ci.cpython-37m-x86_64-linux-gnu.so
orbkit/detci/cy_occ_check.pyx
orbkit/detci/cy_occ_check.cpython-37m-x86_64-linux-gnu.so
orbkit/detci/reduced_density.py
orbkit/detci/cy_ci.pyx
orbkit/detci/ci_core.py
orbkit/detci/occ_check.py
orbkit/detci/ci_read/gamess.py
orbkit/detci/ci_read/psi4.py
orbkit/detci/ci_read/tools.py
orbkit/detci/ci_read/tmol.py
orbkit/detci/ci_read/high_level.py
orbkit/detci/ci_read/__init__.py
orbkit/detci/ci_read/molpro.py
orbkit/detci/ci_read/gaussian.py
orbkit/supporting_data/Atomic_Weights_NIST.html
orbkit/supporting_data/__init__.py
orbkit/output/amira.py
orbkit/output/native.py
orbkit/output/tools.py
orbkit/output/hdf5.py
orbkit/output/xyz.py
orbkit/output/high_level.py
orbkit/output/__init__.py
orbkit/output/vmd_network_draft.py
orbkit/output/cube.py
orbkit/output/hx_network_draft.py
orbkit/output/mayavi_interface.py
orbkit/output/pdb.py
orbkit/output/vmd.py
orbkit/libcint_interface/ao_integrals.py
orbkit/libcint_interface/__init__.py
orbkit/libcint_interface/cy_mo_integrals.cpython-37m-x86_64-linux-gnu.so
orbkit/libcint_interface/cy_mo_integrals.pyx
orbkit/libcint_interface/mo_integrals.py
orbkit/libcint_interface/symmetry.py
orbkit/libcint_interface/fcidump_generator.py
orbkit/read/gamess.py
orbkit/read/wfx.py
orbkit/read/native.py
orbkit/read/tools.py
orbkit/read/molden.py
orbkit-1.1.0.dev2.dist-info/RECORD
orbkit-1.1.0.dev2.dist-info/WHEEL
orbkit-1.1.0.dev2.dist-info/METADATA
orbkit-1.1.0.dev2.dist-info/LICENSE
orbkit-1.1.0.dev2.dist-info/entry_points.txt
orbkit-1.1.0.dev2.dist-info/top_level.txt
